fsm_assignment/vending_machine/vending_fsm.v
`timescale 1ns / 1ps

module vending_fsm (
    input  wire clk,
    input  wire reset,
    input  wire [1:0] coin,
    output reg  dispense,
    output reg  chg5
);

    parameter S0 = 2'd0,
              S1 = 2'd1,
              S2 = 2'd2,
              S3 = 2'd3;

    reg [1:0] state, next_state;

    always @(*) begin
        case (state)
            S0: next_state = (coin == 2'b01) ? S1 :
                             (coin == 2'b10) ? S2 : S0;
            S1: next_state = (coin == 2'b01) ? S2 :
                             (coin == 2'b10) ? S3 : S1;
            S2: next_state = (coin == 2'b01) ? S3 :
                             (coin == 2'b10) ? S0 : S2;
            S3: next_state = (coin == 2'b01) ? S0 :
                             (coin == 2'b10) ? S0 : S3;
            default: next_state = S0;
        endcase
    end

    always @(posedge clk or posedge reset) begin
        if (reset) begin
            state <= S0;
            dispense <= 0;
            chg5 <= 0;
        end 
        else begin
            state <= next_state;
            dispense <= ((state == S3 && coin == 2'b01) ||
                         (state == S3 && coin == 2'b10) ||
                         (state == S2 && coin == 2'b10));
            chg5 <= (state == S3 && coin == 2'b10);
        end
    end

endmodule

fsm_assignment/vending_machine/tb_vending.v
`timescale 1ns / 1ps

module tb_vending;
    reg clk, reset;
    reg [1:0] coin;
    wire dispense, chg5;

    vending_fsm uut (
        .clk(clk), .reset(reset), .coin(coin),
        .dispense(dispense), .chg5(chg5)
    );

    initial clk = 0;
    always #5 clk = ~clk;

    initial begin
        reset = 1; coin = 2'b00;
        #12 reset = 0;

        #10 coin = 2'b01;
        #10 coin = 2'b00;
        #10 coin = 2'b10;
        #10 coin = 2'b00;
        #10 coin = 2'b01;
        #10 coin = 2'b00;
        #10 coin = 2'b10;
        #10 coin = 2'b00;
        #10 coin = 2'b10;
        #10 coin = 2'b00;
        #10 coin = 2'b10;
        #10 coin = 2'b00;
        #10 coin = 2'b10;
        #10 coin = 2'b00;
        #10 coin = 2'b10;
        #10 coin = 2'b01;
        #10 coin = 2'b10;
        #10 coin = 2'b00;

        #50 $finish;
    end

    initial $monitor("t=%0t | coin=%b | dispense=%b | chg5=%b | state=%0d",
                     $time, coin, dispense, chg5, uut.state);

    initial begin
        $dumpfile("wave_vending.vcd");
        $dumpvars(1, tb_vending);
    end
endmodule

fsm_assignment/vending_machine/wave_vending.vcd
$date
	Tue Aug 19 18:58:45 2025
$end
$version
	Icarus Verilog
$end
$timescale
	1ps
$end
$scope module tb_vending $end
$var wire 1 ! dispense $end
$var wire 1 " chg5 $end
$var reg 1 # clk $end
$var reg 2 $ coin [1:0] $end
$var reg 1 % reset $end
$upscope $end
$enddefinitions $end
$comment Show the parameter values. $end
$dumpall
$end
#0
$dumpvars
1%
b0 $
0#
0"
0!
$end
#5000
1#
#10000
0#
#12000
0%
#15000
1#
#20000
0#
#22000
b1 $
#25000
1#
#30000
0#
#32000
b0 $
#35000
1#
#40000
0#
#42000
b10 $
#45000
1#
#50000
0#
#52000
b0 $
#55000
1#
#60000
0#
#62000
b1 $
#65000
1!
1#
#70000
0#
#72000
b0 $
#75000
0!
1#
#80000
0#
#82000
b10 $
#85000
1#
#90000
0#
#92000
b0 $
#95000
1#
#100000
0#
#102000
b10 $
#105000
1!
1#
#110000
0#
#112000
b0 $
#115000
0!
1#
#120000
0#
#122000
b10 $
#125000
1#
#130000
0#
#132000
b0 $
#135000
1#
#140000
0#
#142000
b10 $
#145000
1!
1#
#150000
0#
#152000
b0 $
#155000
0!
1#
#160000
0#
#162000
b10 $
#165000
1#
#170000
0#
#172000
b1 $
#175000
1#
#180000
0#
#182000
b10 $
#185000
1"
1!
1#
#190000
0#
#192000
b0 $
#195000
0"
0!
1#
